LICENSE.txt
MANIFEST.in
README.md
setup.cfg
setup.py
contrib/pylogchop
contrib/pylogchop.ini
contrib/template.json
pylogchop/__init__.py
pylogchop/schemas.py
pylogchop/worker.py
pylogchop.egg-info/PKG-INFO
pylogchop.egg-info/SOURCES.txt
pylogchop.egg-info/dependency_links.txt
pylogchop.egg-info/requires.txt
pylogchop.egg-info/top_level.txt