Metadata-Version: 1.1
Name: pylogchop
Version: 0.0.7
Summary: Log file to syslog shipper
Home-page: https://github.com/schlitzered/pylogchop
Author: schlitzer
Author-email: stephan.schultchen@gmail.com
License: MIT
Platform: posix
Classifier: License :: OSI Approved :: MIT License
Classifier: Programming Language :: Python :: 3
